firefly/__init__.py
firefly/_enums.py
firefly/_exceptions.py
firefly/_structures.py
firefly/_window.py
firefly_py-1.0.0.dist-info/LICENSE
firefly_py-1.0.0.dist-info/METADATA
firefly_py-1.0.0.dist-info/WHEEL
firefly_py-1.0.0.dist-info/RECORD
