Metadata-Version: 2.3
Name: firefly.py
Version: 1.0.0
Summary: Python 基于图像识别的窗口自动化库 | Python-based window automation library with image recognition.
License: MIT
Author: GuangChen23333
Author-email: guangchenworks@outlook.com
Requires-Python: >=3.11
Classifier: License :: OSI Approved :: MIT License
Classifier: Programming Language :: Python :: 3
Classifier: Programming Language :: Python :: 3.11
Classifier: Programming Language :: Python :: 3.12
Classifier: Programming Language :: Python :: 3.13
Requires-Dist: opencv-python (>=4.11.0.86,<5.0.0.0)
Requires-Dist: pillow (>=11.1.0,<12.0.0)
Requires-Dist: psutil (>=7.0.0,<8.0.0)
Requires-Dist: pyautogui (>=0.9.54,<0.10.0)
Requires-Dist: pywin32 (>=308,<309)
Project-URL: Bug Tracker, https://github.com/GuangChen2333/firefly.py/issues
Project-URL: Repository, https://github.com/GuangChen2333/firefly.py
